highla/__init__.py
highla/main.py
highla/version.py
highla-0.1.2.dist-info/METADATA
highla-0.1.2.dist-info/WHEEL
highla-0.1.2.dist-info/entry_points.txt
highla-0.1.2.dist-info/licenses/LICENSE
highla-0.1.2.dist-info/RECORD
