Metadata-Version: 2.3
Name: highla
Version: 0.1.2
Summary: Run diagnostics on high Load Average
Project-URL: Homepage, https://github.com/yaroslaff/highla
Project-URL: Issues, https://github.com/yaroslaff/highla/issues
Author-email: Yaroslav Polyakov <yaroslaff@gmail.com>
Keywords: ddos,diagnostic,load,load average,load-average,mariadb,monitoring,mysql,netstat,performance,postgresql,top,uptime,usage
Classifier: License :: OSI Approved :: MIT License
Classifier: Operating System :: OS Independent
Classifier: Programming Language :: Python :: 3
Classifier: Topic :: System :: Monitoring
Classifier: Topic :: System :: Networking :: Monitoring
Requires-Python: >=3.8
Requires-Dist: psutil>=6.0.0
